birdhousebuilder.recipe.solr-0.2.2-py2.7-nspkg.pth
birdhousebuilder/recipe/solr/README.txt
birdhousebuilder/recipe/solr/__init__.py
birdhousebuilder/recipe/solr/solr.py
birdhousebuilder/recipe/solr/templates/core.properties
birdhousebuilder/recipe/solr/templates/log4j.properties
birdhousebuilder/recipe/solr/templates/schema.xml
birdhousebuilder/recipe/solr/templates/solr-jetty-context.xml
birdhousebuilder/recipe/solr/templates/solr.in.sh
birdhousebuilder/recipe/solr/templates/solr.xml
birdhousebuilder/recipe/solr/templates/solrconfig.xml
birdhousebuilder/recipe/solr/tests/__init__.py
birdhousebuilder/recipe/solr/tests/test_doctests.py
birdhousebuilder.recipe.solr-0.2.2.dist-info/DESCRIPTION.rst
birdhousebuilder.recipe.solr-0.2.2.dist-info/METADATA
birdhousebuilder.recipe.solr-0.2.2.dist-info/RECORD
birdhousebuilder.recipe.solr-0.2.2.dist-info/WHEEL
birdhousebuilder.recipe.solr-0.2.2.dist-info/entry_points.txt
birdhousebuilder.recipe.solr-0.2.2.dist-info/metadata.json
birdhousebuilder.recipe.solr-0.2.2.dist-info/namespace_packages.txt
birdhousebuilder.recipe.solr-0.2.2.dist-info/pbr.json
birdhousebuilder.recipe.solr-0.2.2.dist-info/top_level.txt
