Metadata-Version: 2.0
Name: birdhousebuilder.recipe.solr
Version: 0.2.2
Summary: A Buildout recipe to install and configure Apache Solr with Anaconda.
Home-page: https://github.com/bird-house/birdhousebuilder.recipe.solr
Author: Birdhouse
Author-email: wps-dev@dkrz.de
License: Apache License 2
Keywords: buildout recipe solr birdhouse conda anaconda
Platform: UNKNOWN
Classifier: Framework :: Buildout
Classifier: Intended Audience :: Developers
Classifier: Topic :: Software Development :: Build Tools
Classifier: Topic :: Software Development :: Libraries :: Python Modules
Classifier: License :: OSI Approved :: BSD License
Requires-Dist: Mako
Requires-Dist: birdhousebuilder.recipe.conda (>=0.3.3)
Requires-Dist: birdhousebuilder.recipe.supervisor (>=0.3.4)
Requires-Dist: setuptools
Requires-Dist: zc.buildout
Requires-Dist: zc.recipe.deployment (>=1.3.0)
Provides-Extra: tests
Requires-Dist: zc.buildout; extra == 'tests'
Requires-Dist: zope.testing; extra == 'tests'
